pandora/check_configuration.py
pandora/common.py
pandora/constants.py
pandora/criteria.py
pandora/img_tools.py
pandora/interval_tools.py
pandora/marge.py
pandora/output_tree_design.py
pandora/Pandora.py
pandora/profiler.py
pandora/py.typed
pandora/state_machine.py
pandora/__init__.py
pandora/aggregation/aggregation.py
pandora/aggregation/cbca.py
pandora/aggregation/__init__.py
pandora/aggregation/cpp/aggregation_cpp.cp39-win_amd64.dll.a
pandora/aggregation/cpp/aggregation_cpp.cp39-win_amd64.pyd
pandora/aggregation/cpp/aggregation_cpp.pyi
pandora/aggregation/cpp/meson.build
pandora/aggregation/cpp/__init__.py
pandora/aggregation/cpp/includes/aggregation.hpp
pandora/aggregation/cpp/src/aggregation.cpp
pandora/aggregation/cpp/src/bindings.cpp
pandora/cost_volume_confidence/ambiguity.py
pandora/cost_volume_confidence/cost_volume_confidence.py
pandora/cost_volume_confidence/interval_bounds.py
pandora/cost_volume_confidence/risk.py
pandora/cost_volume_confidence/std_intensity.py
pandora/cost_volume_confidence/__init__.py
pandora/cost_volume_confidence/cpp/cost_volume_confidence_cpp.cp39-win_amd64.dll.a
pandora/cost_volume_confidence/cpp/cost_volume_confidence_cpp.cp39-win_amd64.pyd
pandora/cost_volume_confidence/cpp/cost_volume_confidence_cpp.pyi
pandora/cost_volume_confidence/cpp/meson.build
pandora/cost_volume_confidence/cpp/__init__.py
pandora/cost_volume_confidence/cpp/includes/ambiguity.hpp
pandora/cost_volume_confidence/cpp/includes/cost_volume_confidence_tools.hpp
pandora/cost_volume_confidence/cpp/includes/interval_bounds.hpp
pandora/cost_volume_confidence/cpp/includes/risk.hpp
pandora/cost_volume_confidence/cpp/src/ambiguity.cpp
pandora/cost_volume_confidence/cpp/src/bindings.cpp
pandora/cost_volume_confidence/cpp/src/cost_volume_confidence_tools.cpp
pandora/cost_volume_confidence/cpp/src/interval_bounds.cpp
pandora/cost_volume_confidence/cpp/src/risk.cpp
pandora/cpp/criteria_cpp.cp39-win_amd64.dll.a
pandora/cpp/criteria_cpp.cp39-win_amd64.pyd
pandora-1.7.2.dist-info/DELVEWHEEL
pandora-1.7.2.dist-info/entry_points.txt
pandora-1.7.2.dist-info/METADATA
pandora-1.7.2.dist-info/RECORD
pandora-1.7.2.dist-info/WHEEL
