Metadata-Version: 2.1
Name: pandora
Version: 1.7.2
Summary: Pandora is a stereo matching framework that helps emulate state of the art algorithms
Author: CNES
Requires-Python: >=3.8
Requires-Dist: numpy
Requires-Dist: xarray>=0.13.0
Requires-Dist: scipy
Requires-Dist: rasterio
Requires-Dist: json-checker
Requires-Dist: transitions
Requires-Dist: scikit-image>=0.19.0
Requires-Dist: importlib-metadata; python_version < "3.10"
Provides-Extra: dev
Requires-Dist: pandora[test]; extra == "dev"
Requires-Dist: pandora[docs]; extra == "dev"
Requires-Dist: pylint; extra == "dev"
Requires-Dist: pre-commit; extra == "dev"
Requires-Dist: mypy; extra == "dev"
Requires-Dist: black; extra == "dev"
Requires-Dist: types-setuptools; extra == "dev"
Requires-Dist: build; extra == "dev"
Requires-Dist: cibuildwheel==2.22.0; extra == "dev"
Requires-Dist: psutil; extra == "dev"
Requires-Dist: plotly; extra == "dev"
Provides-Extra: test
Requires-Dist: pytest; extra == "test"
Requires-Dist: pytest-cov; extra == "test"
Requires-Dist: pytest-mock; extra == "test"
Provides-Extra: sgm
Requires-Dist: pandora_plugin_libsgm>=1.5.4; extra == "sgm"
Provides-Extra: mccnn
Requires-Dist: pandora_plugin_mccnn>=1.3.3; extra == "mccnn"
Provides-Extra: docs
Requires-Dist: sphinx; extra == "docs"
Requires-Dist: sphinx_rtd_theme; extra == "docs"
Requires-Dist: sphinx_autoapi; extra == "docs"
Requires-Dist: sphinx_tabs; extra == "docs"
Provides-Extra: notebook
Requires-Dist: jupyter-dash; extra == "notebook"
Requires-Dist: plotly; extra == "notebook"
Requires-Dist: bokeh>=3; extra == "notebook"
Requires-Dist: matplotlib; extra == "notebook"
Requires-Dist: graphviz; extra == "notebook"
Requires-Dist: notebook; extra == "notebook"
Requires-Dist: ipykernel; extra == "notebook"
